scllm/__init__.py
scllm/cluster.py
scllm/py.typed
scllm/pl/__init__.py
scllm/pl/factor_embedding.py
scllm/pl/factor_ridge.py
scllm/pl/factor_stripplot.py
scllm/pl/utils.py
scllm/tl/__init__.py
scllm/tl/base.py
scllm/tl/chains.py
scllm/tl/legacy.py
scllm/tl/model.py
scllm/tl/parser.py
scllm/tl/prompts.py
scllm/tl/utils.py
scllm/tl/validator.py
scllm-0.2.1.dist-info/METADATA
scllm-0.2.1.dist-info/WHEEL
scllm-0.2.1.dist-info/RECORD
