Metadata-Version: 2.4
Name: scllm
Version: 0.2.1
Summary: scllm is a Python package for single-cell analysis using LLMs.
Project-URL: Homepage, https://github.com/sagar87/scllm
Project-URL: Documentation, https://haraldvohringer.com/scllm/
Project-URL: Repository, https://github.com/sagar87/scllm
Project-URL: Bug Tracker, https://github.com/sagar87/scllm/issues
Author-email: Harald Vohringer <harald.voeh@gmail.com>
License: MIT
Keywords: bioinformatics,llm,single-cell
Classifier: Development Status :: 3 - Alpha
Classifier: Intended Audience :: Science/Research
Classifier: License :: OSI Approved :: MIT License
Classifier: Programming Language :: Python :: 3
Classifier: Programming Language :: Python :: 3.12
Classifier: Topic :: Scientific/Engineering :: Bio-Informatics
Requires-Python: >=3.10
Requires-Dist: docarray>=0.40.0
Requires-Dist: fastapi>=0.115.8
Requires-Dist: google-search-results>=2.4.2
Requires-Dist: joypy>=0.2.6
Requires-Dist: langchain-community>=0.3.5
Requires-Dist: langchain-core>=0.3.15
Requires-Dist: langchain-openai>=0.2.5
Requires-Dist: langchain>=0.3.7
Requires-Dist: langsmith>=0.1.139
Requires-Dist: scanpy>=1.11.0
Requires-Dist: uvicorn>=0.34.0
